ati_crewai/__init__.py
ati_crewai/instrumentor.py
ati_integrations_crewai-0.1.1.dist-info/METADATA
ati_integrations_crewai-0.1.1.dist-info/WHEEL
ati_integrations_crewai-0.1.1.dist-info/RECORD
